ECIOTRecruitment/Question3.v
// Y = A.B + B.C + A.C

// 1) BEHAVIORAL LEVEL

module maj3_behavioral(
    input  A, B, C,
    output reg Y
);
    always @(*) begin
        case ({A, B, C})
            3'b000: Y = 1'b0;
            3'b001: Y = 1'b0;
            3'b010: Y = 1'b0;
            3'b011: Y = 1'b1;
            3'b100: Y = 1'b0;
            3'b101: Y = 1'b1;
            3'b110: Y = 1'b1;
            3'b111: Y = 1'b1;
            default: Y = 1'bx;
        endcase
    end
endmodule



// 2) DATAFLOW LEVEL

module maj3_dataflow(
    input  A, B, C,
    output Y
);
    assign Y = (A & B) | (B & C) | (A & C);
endmodule



// 3) GATE LEVEL

module maj3_gate(
    input  A, B, C,
    output Y
);
    wire w1, w2, w3;

    and and1 (w1, A, B);
    and and2 (w2, B, C);
    and and3 (w3, A, C);
    or  or1  (Y, w1, w2, w3);
endmodule



// 4) SWITCH LEVEL (built from nmos/pmos primitives)


module maj3_switch(
    input  A, B, C,
    output Y
);
    supply1 vdd;
    supply0 gnd;
    wire [0:2] PUN;
    wire [0:2] PDN;
    
    pmos p1a(PUN[0], vdd, A);
    pmos p1b(PUN[0], vdd, B);

    pmos p2a(PUN[1], PUN[0], B);
    pmos p3a(PUN[1], PUN[0], C);

    pmos p2b(PUN[2], PUN[1], C);
    pmos p3b(PUN[2], PUN[1], A);

    nmos n1a(PUN[2], PDN[0], A);
    nmos n1b(PDN[0], gnd, B);

    nmos n2a(PUN[2], PDN[1], B);
    nmos n2b(PDN[1], gnd, C);

    nmos n3a(PUN[2], PDN[2], C);
    nmos n3b(PDN[2], gnd, A);

    pmos p_inv(Y, vdd, PUN[2]);
    nmos n_inv(Y, gnd, PUN[2]);    

endmodule


// Testbench - exercises all four implementations together

module tb_maj3;
    reg A, B, C;
    wire Y_beh, Y_flow, Y_gate, Y_sw;

    maj3_behavioral u1(.A(A), .B(B), .C(C), .Y(Y_beh));
    maj3_dataflow   u2(.A(A), .B(B), .C(C), .Y(Y_flow));
    maj3_gate       u3(.A(A), .B(B), .C(C), .Y(Y_gate));
    maj3_switch     u4(.A(A), .B(B), .C(C), .Y(Y_sw));

    initial begin
        $monitor("t=%0t A=%b B=%b C=%b | beh=%b flow=%b gate=%b sw=%b",
                  $time, A, B, C, Y_beh, Y_flow, Y_gate, Y_sw);
        $dumpfile("Question3_test.vcd");
        $dumpvars(0, tb_maj3);

        A=0; B=0; C=0; #10;
        A=0; B=0; C=1; #10;
        A=0; B=1; C=0; #10;
        A=0; B=1; C=1; #10;
        A=1; B=0; C=0; #10;
        A=1; B=0; C=1; #10;
        A=1; B=1; C=0; #10;
        A=1; B=1; C=1; #10;
        $finish;
    end
endmodule

ECIOTRecruitment/Question3_test.vcd
$date
	Sat Jul  4 12:09:29 2026
$end
$version
	Icarus Verilog
$end
$timescale
	1s
$end
$scope module tb_maj3 $end
$var wire 1 ! Y_sw $end
$var wire 1 " Y_gate $end
$var wire 1 # Y_flow $end
$var wire 1 $ Y_beh $end
$var reg 1 % A $end
$var reg 1 & B $end
$var reg 1 ' C $end
$scope module u1 $end
$var wire 1 % A $end
$var wire 1 & B $end
$var wire 1 ' C $end
$var reg 1 $ Y $end
$upscope $end
$scope module u2 $end
$var wire 1 % A $end
$var wire 1 & B $end
$var wire 1 ' C $end
$var wire 1 # Y $end
$upscope $end
$scope module u3 $end
$var wire 1 % A $end
$var wire 1 & B $end
$var wire 1 ' C $end
$var wire 1 " Y $end
$var wire 1 ( w1 $end
$var wire 1 ) w2 $end
$var wire 1 * w3 $end
$upscope $end
$scope module u4 $end
$var wire 1 % A $end
$var wire 1 & B $end
$var wire 1 ' C $end
$var wire 3 + PUN [0:2] $end
$var wire 1 ! Y $end
$var wire 1 , gnd $end
$var wire 1 - vdd $end
$var wire 3 . PDN [0:2] $end
$upscope $end
$upscope $end
$enddefinitions $end
$comment Show the parameter values. $end
$dumpall
$end
#0
$dumpvars
bz .
1-
0,
b111 +
0*
0)
0(
0'
0&
0%
0$
0#
0"
0!
$end
#10
bz0z .
1'
#20
0!
0'
b0zz .
b111 +
1&
#30
1#
1"
1!
1$
1)
b1z0 +
b0z .
1'
#40
0#
0"
0!
0)
0$
0'
0&
b111 +
bz0 .
1%
#50
1#
1"
1$
1*
1!
bz00 .
b110 +
1'
#60
0*
1!
1(
0'
bz0 +
b0z0 .
1&
#70
1)
1*
b0 .
1'
