FiniteStateMachine/SequenceDetector.v
//Sequence detector for sequence 0110
module seq_detector(x, clk, reset, z);
    input x, clk, reset;
    output reg z;
    parameter S0=0, S1=1, S2=2, S3=3;
    reg [0:1] PS, NS;

    always @ (posedge clk or posedge reset)
        if (reset)  PS <= S0;
        else        PS <= NS;

    always @(PS, x)
        case (PS)
            S0: begin
                z = x ? 0 : 0;
                NS = x ? S0 : S1;
            end
            S1: begin
                z = x ? 0 : 0;
                NS = x ? S2 : S1;
            end
            S2: begin
                z = x ? 0 : 0;
                NS = x ? S3 : S1;
            end
            S3: begin
                z = x ? 0 : 1;
                NS = x ? S0 : S1;
            end
        endcase

endmodule

FiniteStateMachine/testSequence.v
module test_sequence;
    reg clk, x, reset;
    wire z;

    seq_detector SEQ(x, clk, reset, z);

    initial begin
        $dumpfile ("sequence.vcd");
        $dumpvars (0, test_sequence);
        clk = 1'b0;
        reset = 1'b1;
        #15 reset = 1'b0;
    end

    always #5 clk = ~clk;

    initial begin
        #12 x = 0; #10 x = 0; #10 x = 1; #10 x = 1;
        #10 x = 0; #10 x = 1; #10 x = 1; #10 x = 0;
        #10 x = 0; #10 x = 1; #10 x = 1; #10 x = 0;
        #10 $finish;
    end

endmodule

FiniteStateMachine/sequence.vcd
$date
	Sun Jun 28 12:53:33 2026
$end
$version
	Icarus Verilog
$end
$timescale
	1s
$end
$scope module test_sequence $end
$var wire 1 ! z $end
$var reg 1 " clk $end
$var reg 1 # reset $end
$var reg 1 $ x $end
$scope module SEQ $end
$var wire 1 " clk $end
$var wire 1 # reset $end
$var wire 1 $ x $end
$var parameter 32 % S0 $end
$var parameter 32 & S1 $end
$var parameter 32 ' S2 $end
$var parameter 32 ( S3 $end
$var reg 2 ) NS [0:1] $end
$var reg 2 * PS [0:1] $end
$var reg 1 ! z $end
$upscope $end
$upscope $end
$enddefinitions $end
$comment Show the parameter values. $end
$dumpall
b11 (
b10 '
b1 &
b0 %
$end
#0
$dumpvars
b0 *
b0x )
x$
1#
0"
0!
$end
#5
1"
#10
0"
#12
b1 )
0$
#15
b1 *
1"
0#
#20
0"
#25
1"
#30
0"
#32
b10 )
1$
#35
b11 )
b10 *
1"
#40
0"
#45
b0 )
b11 *
1"
#50
0"
#52
b1 )
1!
0$
#55
0!
b1 *
1"
#60
0"
#62
b10 )
1$
#65
b11 )
b10 *
1"
#70
0"
#75
b0 )
b11 *
1"
#80
0"
#82
b1 )
1!
0$
#85
0!
b1 *
1"
#90
0"
#95
1"
#100
0"
#102
b10 )
1$
#105
b11 )
b10 *
1"
#110
0"
#115
b0 )
b11 *
1"
#120
0"
#122
b1 )
1!
0$
#125
0!
b1 *
1"
