FiniteStateMachine/SequenceDetector2.v
//Sequence detector for sequence 101010
module seq_detector(x, clk, reset, z);
    input x, clk, reset;
    output reg z;
    parameter S0=0, S1=1, S2=2, S3=3, S4=4, S5=5;
    reg [0:2] PS, NS;

    always @ (posedge clk or posedge reset)
        if (reset)  PS <= S0;
        else        PS <= NS;

    always @(PS, x)
        case (PS)
            S0: begin
                z = x ? 0 : 0;
                NS = x ? S1 : S0;
            end
            S1: begin
                z = x ? 0 : 0;
                NS = x ? S1 : S2;
            end
            S2: begin
                z = x ? 0 : 0;
                NS = x ? S3 : S0;
            end
            S3: begin
                z = x ? 0 : 0;
                NS = x ? S1 : S4;
            end
            S4: begin
                z = x ? 0 : 0;
                NS = x ? S5 : S0;
            end
            S5: begin
                z = x ? 0 : 1;
                NS = x ? S1 : S4;
            end
        endcase

endmodule

FiniteStateMachine/testSequence.v
module test_sequence;
    reg clk, x, reset;
    wire z;

    seq_detector SEQ(x, clk, reset, z);

    initial begin
        $dumpfile ("sequence.vcd");
        $dumpvars (0, test_sequence);
        clk = 1'b0;
        reset = 1'b1;
        #15 reset = 1'b0;
    end

    always #5 clk = ~clk;

    initial begin
        #12 x = 0; #10 x = 0; #10 x = 1; #10 x = 1;
        #10 x = 0; #10 x = 1; #10 x = 1; #10 x = 0;
        #10 x = 0; #10 x = 1; #10 x = 1; #10 x = 0;
        #10 $finish;
    end

endmodule

FiniteStateMachine/sequence2.vcd
$date
	Sun Jun 28 13:27:58 2026
$end
$version
	Icarus Verilog
$end
$timescale
	1s
$end
$scope module test_sequence $end
$var wire 1 ! z $end
$var reg 1 " clk $end
$var reg 1 # reset $end
$var reg 1 $ x $end
$scope module SEQ $end
$var wire 1 " clk $end
$var wire 1 # reset $end
$var wire 1 $ x $end
$var parameter 32 % S0 $end
$var parameter 32 & S1 $end
$var parameter 32 ' S2 $end
$var parameter 32 ( S3 $end
$var parameter 32 ) S4 $end
$var parameter 32 * S5 $end
$var reg 3 + NS [0:2] $end
$var reg 3 , PS [0:2] $end
$var reg 1 ! z $end
$upscope $end
$upscope $end
$enddefinitions $end
$comment Show the parameter values. $end
$dumpall
b101 *
b100 )
b11 (
b10 '
b1 &
b0 %
$end
#0
$dumpvars
b0 ,
b0x +
x$
1#
0"
0!
$end
#5
1"
#10
0"
#12
b0 +
0$
#15
1"
0#
#20
0"
#25
1"
#30
0"
#32
b1 +
1$
#35
b1 ,
1"
#40
0"
#45
1"
#50
0"
#55
1"
#60
0"
#62
b10 +
0$
#65
b0 +
b10 ,
1"
#70
0"
#72
b11 +
1$
#75
b1 +
b11 ,
1"
#80
0"
#82
b100 +
0$
#85
b0 +
b100 ,
1"
#90
0"
#92
b101 +
1$
#95
b1 +
b101 ,
1"
#100
0"
#102
b100 +
1!
0$
#105
b0 +
0!
b100 ,
1"
#110
0"
#112
b101 +
1$
#115
b1 +
b101 ,
1"
#120
0"
#122
b100 +
1!
0$
#125
b0 +
0!
b100 ,
1"
#130
0"
#132
b101 +
1$
#135
b1 +
b101 ,
1"
#140
0"
#142
b100 +
1!
0$
#145
b0 +
0!
b100 ,
1"
#150
0"
#152
b101 +
1$
#155
b1 +
b101 ,
1"
#160
0"
#162
b100 +
1!
0$
#165
b0 +
0!
b100 ,
1"
#170
0"
#172
b101 +
1$
#175
b1 +
b101 ,
1"
#180
0"
#182
b100 +
1!
0$
#185
b0 +
0!
b100 ,
1"
#190
0"
#195
b0 ,
1"
#200
0"
#202
b1 +
1$
#205
b1 ,
1"
#210
0"
#215
1"
#220
0"
#222
b10 +
0$
#225
b0 +
b10 ,
1"
#230
0"
#232
b11 +
1$
#235
b1 +
b11 ,
1"
#240
0"
#242
b100 +
0$
#245
b0 +
b100 ,
1"
