Pipeline_Modelling/pipe_ex.v
module pipe_ex (F, A, B, C, D, clk);

    parameter N = 10;

    input [N-1:0] A, B, C, D;
    input clk;
    output [N-1:0] F;
    reg [N-1:0] L12_x1, L12_x2, L12_D, L23_x3, L23_D, L34_F;

    assign F = L34_F;

    always @(posedge clk)
        begin
            L12_x1 <= #4 A + B;
            L12_x2 <= #4 C - D;
            L12_D  <= D;
        end

    always @(posedge clk) 
        begin        
            L23_x3 <= #4 L12_x1 + L12_x2;
            L23_D <= L12_D;
        end

    always @(posedge clk) 
            L34_F <= #6 L23_x3 * L23_D;

endmodule

Pipeline_Modelling/pipe1_test.v
`timescale 1ns/1ps

module pipe1_test;

    parameter N = 10;
    wire [N-1:0] F;
    reg [N-1:0] A, B, C, D;
    reg clk;

    pipe_ex MYPYPE (F, A, B, C, D, clk);

    initial clk = 0;

    always #10 clk = ~clk;

    initial begin
        #5  A = 10; B = 12; C =  6; D = 3;
        #20 A = 10; B = 10; C =  5; D = 3;
        #20 A = 20; B = 11; C =  1; D = 4;
        #20 A = 15; B = 10; C =  8; D = 2;
        #20 A =  8; B = 15; C =  5; D = 0;
        #20 A = 10; B = 20; C =  5; D = 3;
        #20 A = 10; B = 10; C = 30; D = 1;
        #20 A = 30; B =  1; C =  2; D = 4;
    end

    initial begin
        $dumpfile ("pipe1.vcd");
        $dumpvars (0, pipe1_test);
        $monitor ("TIME : %5d, F = %d", $time, F);
        #300 $finish;
    end

endmodule

Pipeline_Modelling/pipe1.vcd
$date
	Sat Jul 18 12:55:33 2026
$end
$version
	Icarus Verilog
$end
$timescale
	1ps
$end
$scope module pipe1_test $end
$var wire 10 ! F [9:0] $end
$var parameter 32 " N $end
$var reg 10 # A [9:0] $end
$var reg 10 $ B [9:0] $end
$var reg 10 % C [9:0] $end
$var reg 10 & D [9:0] $end
$var reg 1 ' clk $end
$scope module MYPYPE $end
$var wire 10 ( A [9:0] $end
$var wire 10 ) B [9:0] $end
$var wire 10 * C [9:0] $end
$var wire 10 + D [9:0] $end
$var wire 10 , F [9:0] $end
$var wire 1 ' clk $end
$var parameter 32 - N $end
$var reg 10 . L12_D [9:0] $end
$var reg 10 / L12_x1 [9:0] $end
$var reg 10 0 L12_x2 [9:0] $end
$var reg 10 1 L23_D [9:0] $end
$var reg 10 2 L23_x3 [9:0] $end
$var reg 10 3 L34_F [9:0] $end
$upscope $end
$upscope $end
$enddefinitions $end
$comment Show the parameter values. $end
$dumpall
b1010 -
b1010 "
$end
#0
$dumpvars
bx 3
bx 2
bx 1
bx 0
bx /
bx .
bx ,
bx +
bx *
bx )
bx (
0'
bx &
bx %
bx $
bx #
bx !
$end
#5000
b11 &
b11 +
b110 %
b110 *
b1100 $
b1100 )
b1010 #
b1010 (
#10000
b11 .
1'
#14000
b11 0
b10110 /
#20000
0'
#25000
b101 %
b101 *
b1010 $
b1010 )
#30000
b11 1
1'
#34000
b11001 2
b10 0
b10100 /
#40000
0'
#45000
b100 &
b100 +
b1 %
b1 *
b1011 $
b1011 )
b10100 #
b10100 (
#50000
b100 .
1'
#54000
b1111111101 0
b11111 /
b10110 2
#56000
b1001011 !
b1001011 ,
b1001011 3
#60000
0'
#65000
b10 &
b10 +
b1000 %
b1000 *
b1010 $
b1010 )
b1111 #
b1111 (
#70000
b100 1
b10 .
1'
#74000
b11100 2
b110 0
b11001 /
#76000
b1000010 !
b1000010 ,
b1000010 3
#80000
0'
#85000
b0 &
b0 +
b101 %
b101 *
b1111 $
b1111 )
b1000 #
b1000 (
#90000
b0 .
b10 1
1'
#94000
b101 0
b10111 /
b11111 2
#96000
b1110000 !
b1110000 ,
b1110000 3
#100000
0'
#105000
b11 &
b11 +
b10100 $
b10100 )
b1010 #
b1010 (
#110000
b0 1
b11 .
1'
#114000
b11100 2
b10 0
b11110 /
#116000
b111110 !
b111110 ,
b111110 3
#120000
0'
#125000
b1 &
b1 +
b11110 %
b11110 *
b1010 $
b1010 )
#130000
b1 .
b11 1
1'
#134000
b11101 0
b10100 /
b100000 2
#136000
b0 !
b0 ,
b0 3
#140000
0'
#145000
b100 &
b100 +
b10 %
b10 *
b1 $
b1 )
b11110 #
b11110 (
#150000
b1 1
b100 .
1'
#154000
b110001 2
b1111111110 0
b11111 /
#156000
b1100000 !
b1100000 ,
b1100000 3
#160000
0'
#170000
b100 1
1'
#174000
b11101 2
#176000
b110001 !
b110001 ,
b110001 3
#180000
0'
#190000
1'
#196000
b1110100 !
b1110100 ,
b1110100 3
